Workbook

Sheet Dashboard
A1: SAAS / EDTECH FINANCIAL MODEL — 3-YEAR FORECAST
A2: Model by Shubham Singh | Change blue inputs in the Assumptions sheet to update all figures
A4: KEY METRICS — DEFAULT SCENARIO
B5: Year 3 ARR (₹) | D5: LTV : CAC | F5: CAC Payback | H5: Gross Margin (Yr 1)
B6: =PnL!D19 -> 22751533 | D6: =UnitEconomics!B11 -> 8 | F6: =UnitEconomics!B12 -> 6.3 | H6: =PnL!B7 -> 0.8
B8: Year 1 Customers (EOP) | D8: Year 3 Customers (EOP) | F8: Annual NRR | H8: Yr 1 Avg Monthly Burn
B9: =Revenue!E14 -> 146 | D9: =Revenue!E38 -> 342 | F9: =UnitEconomics!B18 -> 0.83413197 | H9: =ABS(PnL!B14)/12 -> 53469.543
A12: P&L SNAPSHOT
B13: Year 1 (FY26) | C13: Year 2 (FY27) | D13: Year 3 (FY28) | E13: 3-Yr Total
A14: Revenue (₹) | B14: =PnL!B4 -> 6416345.2 | C14: =PnL!C4 -> 12794147 | D14: =PnL!D4 -> 19627688 | E14: =PnL!E4 -> 38838180
A15: Gross Profit (₹) | B15: =PnL!B6 -> 5133076.1 | C15: =PnL!C6 -> 10235318 | D15: =PnL!D6 -> 15702150 | E15: =PnL!E6 -> 31070544
A16: Gross Margin % | B16: =PnL!B7 -> 0.8 | C16: =PnL!C7 -> 0.8 | D16: =PnL!D7 -> 0.8 | E16: =PnL!E7 -> 0.8
A17: EBITDA (₹) | B17: =PnL!B14 -> 641634.52 | C17: =PnL!C14 -> 1279414.7 | D17: =PnL!D14 -> 1962768.8 | E17: =PnL!E14 -> 3883818
A18: EBITDA Margin % | B18: =PnL!B15 -> 0.1 | C18: =PnL!C15 -> 0.1 | D18: =PnL!D15 -> 0.1 | E18: =PnL!E15 -> 0.1
A19: ARR — EOP (₹) | B19: =PnL!B19 -> 9114408.7 | C19: =PnL!C19 -> 15728985 | D19: =PnL!D19 -> 22751533 | E19: =PnL!E19 -> 22751533
A20: Customers — EOP | B20: =PnL!B18 -> 146 | C20: =PnL!C18 -> 244 | D20: =PnL!D18 -> 342 | E20: =PnL!E18 -> 342
A23: NAVIGATE THE MODEL
A24: Assumptions | B24: Edit all blue inputs here to model different scenarios.
A25: Revenue | B25: Month-by-month MRR build: new customers, churn, expansion, ARR.
A26: UnitEconomics | B26: LTV, CAC, payback period, NRR — with benchmark context.
A27: PnL | B27: 3-year annual P&L: Revenue, Gross Profit, OpEx, EBITDA.
A28: Burn & Runway | B28: Monthly cash model: opening cash, burn rate, closing cash.
A30: COLOR CODING
A31: Blue text — Hardcoded inputs in the Assumptions sheet. Edit freely.
A32: Black text — Formulas. Do not edit.
A33: Green text — Cross-sheet references pulling live data from other tabs.

Sheet Assumptions
A1: MODEL ASSUMPTIONS — SaaS / EdTech
A2: Blue cells are editable inputs. All other cells are formula-driven. Change inputs to model your scenario.
A3: BUSINESS INPUTS
A4: Starting Customers (Month 0) | B4: 50 | C4: Customers already on platform before model starts
A5: New Customers / Month (Year 1) | B5: 10 | C5: Average new logo additions per month
A6: Yr 1 → Yr 2 New Customer Growth | B6: 0.2 | C6: YoY uplift in monthly new-customer pace
A7: Yr 2 → Yr 3 New Customer Growth | B7: 0.15
A8: New Customers / Month (Year 2) | B8: =ROUND(B5*(1+B6),0) -> 12 | C8: Auto-calculated
A9: New Customers / Month (Year 3) | B9: =ROUND(B8*(1+B7),0) -> 14 | C9: Auto-calculated
A11: PRICING & RETENTION
A12: Monthly ARPU (₹) | B12: 5000 | C12: Average Revenue Per User / seat per month
A13: Monthly Logo Churn Rate | B13: 0.02 | C13: % of customers lost each month
A14: Monthly Expansion MRR Rate | B14: 0.005 | C14: Upsell / seat expansion on existing MRR base
A16: UNIT ECONOMICS
A17: Blended CAC (₹) | B17: 25000 | C17: Fully-loaded sales + marketing cost per new customer
A19: COST STRUCTURE (% of Revenue)
A20: COGS | B20: 0.2 | C20: Hosting, content delivery, customer support
A21: Sales & Marketing | B21: 0.35 | C21: Sales team, digital ads, events
A22: R&D / Product | B22: 0.2 | C22: Engineering + product salaries
A23: G&A | B23: 0.15 | C23: Finance, HR, admin, legal
A24: Total OpEx (excl. COGS) | B24: =B21+B22+B23 -> 0.7 | C24: S&M + R&D + G&A
A25: Gross Margin (implied) | B25: =1-B20 -> 0.8
A27: CAPITAL
A28: Starting Cash (₹) | B28: 5000000 | C28: Cash at Month 0 — seed or existing funding

Sheet Revenue
A1: REVENUE MODEL — MONTHLY MRR BUILD-UP (36 Months)
A2: Month | B2: Period | C2: New Custs | D2: Churned Custs | E2: Total Custs (EOP) | F2: New MRR (₹) | G2: Churned MRR (₹) | H2: Expansion MRR (₹) | I2: Net MRR Change (₹) | J2: Total MRR (₹) | K2: ARR (₹)
A3: 1 | B3: Jan '26 | C3: =IF(A3<=12,Assumptions!$B$5,IF(A3<=24,Assumptions!$B$8,Assumptions!$B$9)) -> 10 | D3: =ROUND(Assumptions!$B$4*Assumptions!$B$13,0) -> 1 | E3: =Assumptions!$B$4+C3-D3 -> 59 | F3: =C3*Assumptions!$B$12 -> 50000 | G3: =D3*Assumptions!$B$12 -> 5000 | H3: =Assumptions!$B$4*Assumptions!$B$12*Assumptions!$B$14 -> 1250 | I3: =F3-G3+H3 -> 46250 | J3: =Assumptions!$B$4*Assumptions!$B$12+I3 -> 296250 | K3: =J3*12 -> 3555000
A4: 2 | B4: Feb '26 | C4: =IF(A4<=12,Assumptions!$B$5,IF(A4<=24,Assumptions!$B$8,Assumptions!$B$9)) -> 10 | D4: =ROUND(E3*Assumptions!$B$13,0) -> 1 | E4: =E3+C4-D4 -> 68 | F4: =C4*Assumptions!$B$12 -> 50000 | G4: =D4*Assumptions!$B$12 -> 5000 | H4: =J3*Assumptions!$B$14 -> 1481.25 | I4: =F4-G4+H4 -> 46481.25 | J4: =J3+I4 -> 342731.25 | K4: =J4*12 -> 4112775
A5: 3 | B5: Mar '26 | C5: =IF(A5<=12,Assumptions!$B$5,IF(A5<=24,Assumptions!$B$8,Assumptions!$B$9)) -> 10 | D5: =ROUND(E4*Assumptions!$B$13,0) -> 1 | E5: =E4+C5-D5 -> 77 | F5: =C5*Assumptions!$B$12 -> 50000 | G5: =D5*Assumptions!$B$12 -> 5000 | H5: =J4*Assumptions!$B$14 -> 1713.6562 | I5: =F5-G5+H5 -> 46713.656 | J5: =J4+I5 -> 389444.91 | K5: =J5*12 -> 4673338.9
A6: 4 | B6: Apr '26 | C6: =IF(A6<=12,Assumptions!$B$5,IF(A6<=24,Assumptions!$B$8,Assumptions!$B$9)) -> 10 | D6: =ROUND(E5*Assumptions!$B$13,0) -> 2 | E6: =E5+C6-D6 -> 85 | F6: =C6*Assumptions!$B$12 -> 50000 | G6: =D6*Assumptions!$B$12 -> 10000 | H6: =J5*Assumptions!$B$14 -> 1947.2245 | I6: =F6-G6+H6 -> 41947.225 | J6: =J5+I6 -> 431392.13 | K6: =J6*12 -> 5176705.6
A7: 5 | B7: May '26 | C7: =IF(A7<=12,Assumptions!$B$5,IF(A7<=24,Assumptions!$B$8,Assumptions!$B$9)) -> 10 | D7: =ROUND(E6*Assumptions!$B$13,0) -> 2 | E7: =E6+C7-D7 -> 93 | F7: =C7*Assumptions!$B$12 -> 50000 | G7: =D7*Assumptions!$B$12 -> 10000 | H7: =J6*Assumptions!$B$14 -> 2156.9607 | I7: =F7-G7+H7 -> 42156.961 | J7: =J6+I7 -> 473549.09 | K7: =J7*12 -> 5682589.1
A8: 6 | B8: Jun '26 | C8: =IF(A8<=12,Assumptions!$B$5,IF(A8<=24,Assumptions!$B$8,Assumptions!$B$9)) -> 10 | D8: =ROUND(E7*Assumptions!$B$13,0) -> 2 | E8: =E7+C8-D8 -> 101 | F8: =C8*Assumptions!$B$12 -> 50000 | G8: =D8*Assumptions!$B$12 -> 10000 | H8: =J7*Assumptions!$B$14 -> 2367.7455 | I8: =F8-G8+H8 -> 42367.745 | J8: =J7+I8 -> 515916.84 | K8: =J8*12 -> 6191002
A9: 7 | B9: Jul '26 | C9: =IF(A9<=12,Assumptions!$B$5,IF(A9<=24,Assumptions!$B$8,Assumptions!$B$9)) -> 10 | D9: =ROUND(E8*Assumptions!$B$13,0) -> 2 | E9: =E8+C9-D9 -> 109 | F9: =C9*Assumptions!$B$12 -> 50000 | G9: =D9*Assumptions!$B$12 -> 10000 | H9: =J8*Assumptions!$B$14 -> 2579.5842 | I9: =F9-G9+H9 -> 42579.584 | J9: =J8+I9 -> 558496.42 | K9: =J9*12 -> 6701957.1
A10: 8 | B10: Aug '26 | C10: =IF(A10<=12,Assumptions!$B$5,IF(A10<=24,Assumptions!$B$8,Assumptions!$B$9)) -> 10 | D10: =ROUND(E9*Assumptions!$B$13,0) -> 2 | E10: =E9+C10-D10 -> 117 | F10: =C10*Assumptions!$B$12 -> 50000 | G10: =D10*Assumptions!$B$12 -> 10000 | H10: =J9*Assumptions!$B$14 -> 2792.4821 | I10: =F10-G10+H10 -> 42792.482 | J10: =J9+I10 -> 601288.9 | K10: =J10*12 -> 7215466.8
A11: 9 | B11: Sep '26 | C11: =IF(A11<=12,Assumptions!$B$5,IF(A11<=24,Assumptions!$B$8,Assumptions!$B$9)) -> 10 | D11: =ROUND(E10*Assumptions!$B$13,0) -> 2 | E11: =E10+C11-D11 -> 125 | F11: =C11*Assumptions!$B$12 -> 50000 | G11: =D11*Assumptions!$B$12 -> 10000 | H11: =J10*Assumptions!$B$14 -> 3006.4445 | I11: =F11-G11+H11 -> 43006.445 | J11: =J10+I11 -> 644295.35 | K11: =J11*12 -> 7731544.2
A12: 10 | B12: Oct '26 | C12: =IF(A12<=12,Assumptions!$B$5,IF(A12<=24,Assumptions!$B$8,Assumptions!$B$9)) -> 10 | D12: =ROUND(E11*Assumptions!$B$13,0) -> 3 | E12: =E11+C12-D12 -> 132 | F12: =C12*Assumptions!$B$12 -> 50000 | G12: =D12*Assumptions!$B$12 -> 15000 | H12: =J11*Assumptions!$B$14 -> 3221.4767 | I12: =F12-G12+H12 -> 38221.477 | J12: =J11+I12 -> 682516.82 | K12: =J12*12 -> 8190201.9
A13: 11 | B13: Nov '26 | C13: =IF(A13<=12,Assumptions!$B$5,IF(A13<=24,Assumptions!$B$8,Assumptions!$B$9)) -> 10 | D13: =ROUND(E12*Assumptions!$B$13,0) -> 3 | E13: =E12+C13-D13 -> 139 | F13: =C13*Assumptions!$B$12 -> 50000 | G13: =D13*Assumptions!$B$12 -> 15000 | H13: =J12*Assumptions!$B$14 -> 3412.5841 | I13: =F13-G13+H13 -> 38412.584 | J13: =J12+I13 -> 720929.41 | K13: =J13*12 -> 8651152.9
A14: 12 | B14: Dec '26 | C14: =IF(A14<=12,Assumptions!$B$5,IF(A14<=24,Assumptions!$B$8,Assumptions!$B$9)) -> 10 | D14: =ROUND(E13*Assumptions!$B$13,0) -> 3 | E14: =E13+C14-D14 -> 146 | F14: =C14*Assumptions!$B$12 -> 50000 | G14: =D14*Assumptions!$B$12 -> 15000 | H14: =J13*Assumptions!$B$14 -> 3604.647 | I14: =F14-G14+H14 -> 38604.647 | J14: =J13+I14 -> 759534.06 | K14: =J14*12 -> 9114408.7
A15: 13 | B15: Jan '27 | C15: =IF(A15<=12,Assumptions!$B$5,IF(A15<=24,Assumptions!$B$8,Assumptions!$B$9)) -> 12 | D15: =ROUND(E14*Assumptions!$B$13,0) -> 3 | E15: =E14+C15-D15 -> 155 | F15: =C15*Assumptions!$B$12 -> 60000 | G15: =D15*Assumptions!$B$12 -> 15000 | H15: =J14*Assumptions!$B$14 -> 3797.6703 | I15: =F15-G15+H15 -> 48797.67 | J15: =J14+I15 -> 808331.73 | K15: =J15*12 -> 9699980.7
... A38: 36 | B38: Dec '28 | C38: =IF(A38<=12,Assumptions!$B$5,IF(A38<=24,Assumptions!$B$8,Assumptions!$B$9)) -> 14 | D38: =ROUND(E37*Assumptions!$B$13,0) -> 7 | E38: =E37+C38-D38 -> 342 | F38: =C38*Assumptions!$B$12 -> 70000 | G38: =D38*Assumptions!$B$12 -> 35000 | H38: =J37*Assumptions!$B$14 -> 9258.5129 | I38: =F38-G38+H38 -> 44258.513 | J38: =J37+I38 -> 1895961.1 | K38: =J38*12 -> 22751533
A40: Year 1 Summary | C40: =SUM(C3:C14) -> 120 | D40: =SUM(D3:D14) -> 24 | E40: =E14 -> 146 | F40: =SUM(F3:F14) -> 600000 | G40: =SUM(G3:G14) -> 120000 | H40: =SUM(H3:H14) -> 29534.056 | I40: =SUM(I3:I14) -> 509534.06 | J40: =SUM(J3:J14) -> 6416345.2 | K40: =K14 -> 9114408.7
A41: Year 2 Summary | C41: =SUM(C15:C26) -> 144 | D41: =SUM(D15:D26) -> 46 | E41: =E26 -> 244 | F41: =SUM(F15:F26) -> 720000 | G41: =SUM(G15:G26) -> 230000 | H41: =SUM(H15:H26) -> 61214.661 | I41: =SUM(I15:I26) -> 551214.66 | J41: =SUM(J15:J26) -> 12794147 | K41: =K26 -> 15728985
A42: Year 3 Summary | C42: =SUM(C27:C38) -> 168 | D42: =SUM(D27:D38) -> 70 | E42: =E38 -> 342 | F42: =SUM(F27:F38) -> 840000 | G42: =SUM(G27:G38) -> 350000 | H42: =SUM(H27:H38) -> 95212.376 | I42: =SUM(I27:I38) -> 585212.38 | J42: =SUM(J27:J38) -> 19627688 | K42: =K38 -> 22751533
A44: Year colour: Blue = Year 1 | Green = Year 2 | Amber = Year 3

Sheet UnitEconomics
A1: UNIT ECONOMICS
A3: CAC & LTV
A4: Blended CAC (₹) | B4: =Assumptions!$B$17 -> 25000 | C4: Sales + marketing cost per new customer acquired
A5: Monthly ARPU (₹) | B5: =Assumptions!$B$12 -> 5000 | C5: Average revenue per customer per month
A6: Gross Margin % | B6: =1-Assumptions!$B$20 -> 0.8 | C6: Revenue retained after COGS
A7: Monthly Churn Rate | B7: =Assumptions!$B$13 -> 0.02 | C7: % of customers lost per month
A8: Annual Churn (compounded) | B8: =1-(1-B7)^12 -> 0.21528328 | C8: Formula: 1 − (1 − monthly_churn)^12
A9: Customer Lifetime (months) | B9: =IF(B7=0,999,ROUND(1/B7,1)) -> 50 | C9: Formula: 1 ÷ monthly churn rate
A10: LTV (₹) | B10: =IF(B7=0,0,B5*B6/B7) -> 200000 | C10: Formula: ARPU × Gross Margin ÷ Monthly Churn
A11: LTV : CAC | B11: =IF(B4=0,0,B10/B4) -> 8 | C11: Target ≥ 3x | World-class ≥ 5x
A12: CAC Payback Period (months) | B12: =IF(B5*B6=0,0,ROUND(B4/(B5*B6),1)) -> 6.3 | C12: Target < 18 months for B2B SaaS
A14: RETENTION & EXPANSION
A15: Monthly Logo Churn | B15: =Assumptions!$B$13 -> 0.02
A16: Monthly Expansion Rate | B16: =Assumptions!$B$14 -> 0.005 | C16: Upsell / seat growth on existing base
A17: Monthly Net Revenue Ret. | B17: =1-B15+B16 -> 0.985 | C17: Formula: 1 − Churn + Expansion
A18: Annual NRR | B18: =B17^12 -> 0.83413197 | C18: >100% = revenue grows without new sales
A20: BENCHMARK CONTEXT (B2B SaaS / EdTech)
A21: LTV:CAC < 1x | B21: Losing money on every customer — fix pricing or CAC immediately
A22: LTV:CAC 1–3x | B22: Marginal — revisit pricing model or reduce acquisition cost
A23: LTV:CAC > 3x | B23: Healthy benchmark — industry standard for sustainable SaaS
A24: LTV:CAC > 5x | B24: Exceptional — significant headroom to accelerate growth spend
A25: Payback < 12 mo | B25: Best-in-class — very fast capital efficiency
A26: Payback 12–18 mo | B26: Good for B2B SaaS with annual contracts
A27: Annual NRR > 100% | B27: Expansion > churn — company grows without a single new customer
A28: Annual NRR > 120% | B28: World-class (Snowflake, Twilio) — strong upsell motion

Sheet PnL
A1: PROFIT & LOSS — 3-YEAR ANNUAL SUMMARY
B2: Year 1 (FY26) | C2: Year 2 (FY27) | D2: Year 3 (FY28) | E2: 3-Yr Total
A4: Revenue (MRR collected, ₹) | B4: =SUM(Revenue!J3:J14) -> 6416345.2 | C4: =SUM(Revenue!J15:J26) -> 12794147 | D4: =SUM(Revenue!J27:J38) -> 19627688 | E4: =SUM(B4:D4) -> 38838180
A5: COGS | B5: =B4*Assumptions!$B$20 -> 1283269 | C5: =C4*Assumptions!$B$20 -> 2558829.4 | D5: =D4*Assumptions!$B$20 -> 3925537.5 | E5: =SUM(B5:D5) -> 7767635.9
A6: Gross Profit | B6: =B4-B5 -> 5133076.1 | C6: =C4-C5 -> 10235318 | D6: =D4-D5 -> 15702150 | E6: =SUM(B6:D6) -> 31070544
A7: Gross Margin % | B7: =IF(B4=0,0,B6/B4) -> 0.8 | C7: =IF(C4=0,0,C6/C4) -> 0.8 | D7: =IF(D4=0,0,D6/D4) -> 0.8 | E7: =IF(E4=0,0,E6/E4) -> 0.8
A9: Sales & Marketing | B9: =B4*Assumptions!$B$21 -> 2245720.8 | C9: =C4*Assumptions!$B$21 -> 4477951.4 | D9: =D4*Assumptions!$B$21 -> 6869690.6 | E9: =SUM(B9:D9) -> 13593363
A10: R&D / Product | B10: =B4*Assumptions!$B$22 -> 1283269 | C10: =C4*Assumptions!$B$22 -> 2558829.4 | D10: =D4*Assumptions!$B$22 -> 3925537.5 | E10: =SUM(B10:D10) -> 7767635.9
A11: G&A | B11: =B4*Assumptions!$B$23 -> 962451.78 | C11: =C4*Assumptions!$B$23 -> 1919122 | D11: =D4*Assumptions!$B$23 -> 2944153.1 | E11: =SUM(B11:D11) -> 5825726.9
A12: Total OpEx (excl. COGS) | B12: =B9+B10+B11 -> 4491441.6 | C12: =C9+C10+C11 -> 8955902.9 | D12: =D9+D10+D11 -> 13739381 | E12: =SUM(B12:D12) -> 27186726
A14: EBITDA | B14: =B6-B12 -> 641634.52 | C14: =C6-C12 -> 1279414.7 | D14: =D6-D12 -> 1962768.8 | E14: =SUM(B14:D14) -> 3883818
A15: EBITDA Margin % | B15: =IF(B4=0,0,B14/B4) -> 0.1 | C15: =IF(C4=0,0,C14/C4) -> 0.1 | D15: =IF(D4=0,0,D14/D4) -> 0.1 | E15: =IF(E4=0,0,E14/E4) -> 0.1
A17: KEY OPERATING METRICS
A18: Customers (EOP) | B18: =Revenue!E14 -> 146 | C18: =Revenue!E26 -> 244 | D18: =Revenue!E38 -> 342 | E18: =D18 -> 342
A19: ARR — End of Period (₹) | B19: =Revenue!K14 -> 9114408.7 | C19: =Revenue!K26 -> 15728985 | D19: =Revenue!K38 -> 22751533 | E19: =D19 -> 22751533
A20: Avg Monthly MRR Growth | B20: =IF(Revenue!J3=0,0,(Revenue!J14/Revenue!J3)^(1/11)-1) -> 0.089360735 | C20: =IF(Revenue!J15=0,0,(Revenue!J26/Revenue!J15)^(1/11)-1) -> 0.044923578 | D20: =IF(Revenue!J27=0,0,(Revenue!J38/Revenue!J27)^(1/11)-1) -> 0.030506023 | E20: =AVERAGE(B20:D20) -> 0.054930112
A21: LTV : CAC | B21: =UnitEconomics!B11 -> 8 | C21: =UnitEconomics!B11 -> 8 | D21: =UnitEconomics!B11 -> 8 | E21: =UnitEconomics!B11 -> 8
A22: Annual NRR | B22: =UnitEconomics!B18 -> 0.83413197 | C22: =UnitEconomics!B18 -> 0.83413197 | D22: =UnitEconomics!B18 -> 0.83413197 | E22: =UnitEconomics!B18 -> 0.83413197

Sheet Burn & Runway
A1: BURN & RUNWAY — MONTHLY CASH MODEL (36 Months)
A2: Month | B2: Period | C2: Revenue (₹) | D2: COGS (₹) | E2: Gross Profit (₹) | F2: S&M (₹) | G2: R&D (₹) | H2: G&A (₹) | I2: Total OpEx (₹) | J2: EBITDA / Net Burn (₹) | K2: Opening Cash (₹) | L2: Closing Cash (₹)
A3: 1 | B3: Jan '26 | C3: =Revenue!J3 -> 296250 | D3: =C3*Assumptions!$B$20 -> 59250 | E3: =C3-D3 -> 237000 | F3: =C3*Assumptions!$B$21 -> 103687.5 | G3: =C3*Assumptions!$B$22 -> 59250 | H3: =C3*Assumptions!$B$23 -> 44437.5 | I3: =F3+G3+H3 -> 207375 | J3: =E3-I3 -> 29625 | K3: =Assumptions!$B$28 -> 5000000 | L3: =K3+J3 -> 5029625
A4: 2 | B4: Feb '26 | C4: =Revenue!J4 -> 342731.25 | D4: =C4*Assumptions!$B$20 -> 68546.25 | E4: =C4-D4 -> 274185 | F4: =C4*Assumptions!$B$21 -> 119955.94 | G4: =C4*Assumptions!$B$22 -> 68546.25 | H4: =C4*Assumptions!$B$23 -> 51409.688 | I4: =F4+G4+H4 -> 239911.88 | J4: =E4-I4 -> 34273.125 | K4: =L3 -> 5029625 | L4: =K4+J4 -> 5063898.1
A5: 3 | B5: Mar '26 | C5: =Revenue!J5 -> 389444.91 | D5: =C5*Assumptions!$B$20 -> 77888.981 | E5: =C5-D5 -> 311555.92 | F5: =C5*Assumptions!$B$21 -> 136305.72 | G5: =C5*Assumptions!$B$22 -> 77888.981 | H5: =C5*Assumptions!$B$23 -> 58416.736 | I5: =F5+G5+H5 -> 272611.43 | J5: =E5-I5 -> 38944.491 | K5: =L4 -> 5063898.1 | L5: =K5+J5 -> 5102842.6
A6: 4 | B6: Apr '26 | C6: =Revenue!J6 -> 431392.13 | D6: =C6*Assumptions!$B$20 -> 86278.426 | E6: =C6-D6 -> 345113.7 | F6: =C6*Assumptions!$B$21 -> 150987.25 | G6: =C6*Assumptions!$B$22 -> 86278.426 | H6: =C6*Assumptions!$B$23 -> 64708.82 | I6: =F6+G6+H6 -> 301974.49 | J6: =E6-I6 -> 43139.213 | K6: =L5 -> 5102842.6 | L6: =K6+J6 -> 5145981.8
A7: 5 | B7: May '26 | C7: =Revenue!J7 -> 473549.09 | D7: =C7*Assumptions!$B$20 -> 94709.818 | E7: =C7-D7 -> 378839.27 | F7: =C7*Assumptions!$B$21 -> 165742.18 | G7: =C7*Assumptions!$B$22 -> 94709.818 | H7: =C7*Assumptions!$B$23 -> 71032.364 | I7: =F7+G7+H7 -> 331484.36 | J7: =E7-I7 -> 47354.909 | K7: =L6 -> 5145981.8 | L7: =K7+J7 -> 5193336.7
A8: 6 | B8: Jun '26 | C8: =Revenue!J8 -> 515916.84 | D8: =C8*Assumptions!$B$20 -> 103183.37 | E8: =C8-D8 -> 412733.47 | F8: =C8*Assumptions!$B$21 -> 180570.89 | G8: =C8*Assumptions!$B$22 -> 103183.37 | H8: =C8*Assumptions!$B$23 -> 77387.526 | I8: =F8+G8+H8 -> 361141.79 | J8: =E8-I8 -> 51591.684 | K8: =L7 -> 5193336.7 | L8: =K8+J8 -> 5244928.4
A9: 7 | B9: Jul '26 | C9: =Revenue!J9 -> 558496.42 | D9: =C9*Assumptions!$B$20 -> 111699.28 | E9: =C9-D9 -> 446797.14 | F9: =C9*Assumptions!$B$21 -> 195473.75 | G9: =C9*Assumptions!$B$22 -> 111699.28 | H9: =C9*Assumptions!$B$23 -> 83774.463 | I9: =F9+G9+H9 -> 390947.49 | J9: =E9-I9 -> 55849.642 | K9: =L8 -> 5244928.4 | L9: =K9+J9 -> 5300778.1
A10: 8 | B10: Aug '26 | C10: =Revenue!J10 -> 601288.9 | D10: =C10*Assumptions!$B$20 -> 120257.78 | E10: =C10-D10 -> 481031.12 | F10: =C10*Assumptions!$B$21 -> 210451.12 | G10: =C10*Assumptions!$B$22 -> 120257.78 | H10: =C10*Assumptions!$B$23 -> 90193.335 | I10: =F10+G10+H10 -> 420902.23 | J10: =E10-I10 -> 60128.89 | K10: =L9 -> 5300778.1 | L10: =K10+J10 -> 5360907
A11: 9 | B11: Sep '26 | C11: =Revenue!J11 -> 644295.35 | D11: =C11*Assumptions!$B$20 -> 128859.07 | E11: =C11-D11 -> 515436.28 | F11: =C11*Assumptions!$B$21 -> 225503.37 | G11: =C11*Assumptions!$B$22 -> 128859.07 | H11: =C11*Assumptions!$B$23 -> 96644.302 | I11: =F11+G11+H11 -> 451006.74 | J11: =E11-I11 -> 64429.535 | K11: =L10 -> 5360907 | L11: =K11+J11 -> 5425336.5
A12: 10 | B12: Oct '26 | C12: =Revenue!J12 -> 682516.82 | D12: =C12*Assumptions!$B$20 -> 136503.36 | E12: =C12-D12 -> 546013.46 | F12: =C12*Assumptions!$B$21 -> 238880.89 | G12: =C12*Assumptions!$B$22 -> 136503.36 | H12: =C12*Assumptions!$B$23 -> 102377.52 | I12: =F12+G12+H12 -> 477761.78 | J12: =E12-I12 -> 68251.682 | K12: =L11 -> 5425336.5 | L12: =K12+J12 -> 5493588.2
A13: 11 | B13: Nov '26 | C13: =Revenue!J13 -> 720929.41 | D13: =C13*Assumptions!$B$20 -> 144185.88 | E13: =C13-D13 -> 576743.53 | F13: =C13*Assumptions!$B$21 -> 252325.29 | G13: =C13*Assumptions!$B$22 -> 144185.88 | H13: =C13*Assumptions!$B$23 -> 108139.41 | I13: =F13+G13+H13 -> 504650.59 | J13: =E13-I13 -> 72092.941 | K13: =L12 -> 5493588.2 | L13: =K13+J13 -> 5565681.1
A14: 12 | B14: Dec '26 | C14: =Revenue!J14 -> 759534.06 | D14: =C14*Assumptions!$B$20 -> 151906.81 | E14: =C14-D14 -> 607627.24 | F14: =C14*Assumptions!$B$21 -> 265836.92 | G14: =C14*Assumptions!$B$22 -> 151906.81 | H14: =C14*Assumptions!$B$23 -> 113930.11 | I14: =F14+G14+H14 -> 531673.84 | J14: =E14-I14 -> 75953.406 | K14: =L13 -> 5565681.1 | L14: =K14+J14 -> 5641634.5
A15: 13 | B15: Jan '27 | C15: =Revenue!J15 -> 808331.73 | D15: =C15*Assumptions!$B$20 -> 161666.35 | E15: =C15-D15 -> 646665.38 | F15: =C15*Assumptions!$B$21 -> 282916.1 | G15: =C15*Assumptions!$B$22 -> 161666.35 | H15: =C15*Assumptions!$B$23 -> 121249.76 | I15: =F15+G15+H15 -> 565832.21 | J15: =E15-I15 -> 80833.173 | K15: =L14 -> 5641634.5 | L15: =K15+J15 -> 5722467.7
... A38: 36 | B38: Dec '28 | C38: =Revenue!J38 -> 1895961.1 | D38: =C38*Assumptions!$B$20 -> 379192.22 | E38: =C38-D38 -> 1516768.9 | F38: =C38*Assumptions!$B$21 -> 663586.38 | G38: =C38*Assumptions!$B$22 -> 379192.22 | H38: =C38*Assumptions!$B$23 -> 284394.16 | I38: =F38+G38+H38 -> 1327172.8 | J38: =E38-I38 -> 189596.11 | K38: =L37 -> 8694221.9 | L38: =K38+J38 -> 8883818
A41: RUNWAY SUMMARY
A42: Starting Cash (₹) | C42: =Assumptions!$B$28 -> 5000000
A43: Closing Cash after 36 Months (₹) | C43: =L38 -> 8883818
A44: Avg Monthly Burn — Year 1 (₹) | C44: =ABS(AVERAGE(J3:J14)) -> 53469.543
A45: Avg Monthly Burn — Year 2 (₹) | C45: =ABS(AVERAGE(J15:J26)) -> 106617.89
A46: Cash Status after 36 Months | C46: =IF(L38>=0,"Cash positive throughout 36-month model","Cash depleted — check assumptions") -> Cash positive throughout 36-month model
